<?xml version="1.0" encoding="utf-8" ?><dwsync><file name="bg-bar-white.png" local="-4509692631185358848" remote="-4056243716157894968" testing="0" /><file name="bg-bar.png" local="-4509692631185358848" remote="-4056243458459857208" testing="0" /><file name="bg-content-left.png" local="-4509692631185358848" remote="-4056243458459857208" testing="0" /><file name="bg-content-right.png" local="-4509692631185358848" remote="-4056243458459857208" testing="0" /><file name="bg-content.png" local="-4509692631185358848" remote="-4056243458459857208" testing="0" /><file name="bg-navigation-item-hover.png" local="-4509692631185358848" remote="-4056243458459857208" testing="0" /><file name="bg-navigation-item.png" local="-4509692631185358848" remote="-4056243458459857208" testing="0" /><file name="bg-navigation.png" local="-4509692631185358848" remote="-4056243458459857208" testing="0" /><file name="bg-tab.png" local="-4509692631185358848" remote="-4056243458459857208" testing="0" /><file name="body.png" local="-4509692631185358848" remote="-4056243458459857208" testing="0" /><file name="gradient-inner.png" local="-4509692631185358848" remote="-4056243458459857208" testing="0" /><file name="menu-collapsed-rtl.gif" local="-4384670672979230720" remote="-4056243458459857208" testing="0" /><file name="menu-collapsed.gif" local="-4509692631185358848" remote="-4056243458459857208" testing="0" /><file name="menu-expanded.gif" local="-4509692631185358848" remote="-4056243458459857208" testing="0" /><file name="menu-leaf.gif" local="-4509692631185358848" remote="-4056243458459857208" testing="0" /><file name="task-list.png" local="-4463734037281767424" remote="-4056243458459857208" testing="0" /></dwsync>